{
  "build": {
    "beforeDevCommand": "",
    "beforeBuildCommand": "",
    "devPath": "../",
    "distDir": "../"
  },
  "package": {
    "productName": "TodoApp",
    "version": "1.0.0"
  },
  "tauri": {
    "allowlist": {
      "all": false,
      "shell": {
        "all": false,
        "open": true
      }
    },
    "bundle": {
      "active": true,
      "targets": "all",
      "identifier": "com.todoapp.dev",
      "icon": [
        "icons/32x32.png",
        "icons/128x128.png",
        "icons/128x128@2x.png",
        "icons/icon.icns",
        "icons/icon.ico"
      ]
    },
    "security": {
      "csp": null
    },
    "windows": [
      {
        "fullscreen": false,
        "resizable": true,
        "title": "待办事项",
        "width": 800,
        "height": 600,
        "minWidth": 600,
        "minHeight": 400
      }
    ]
  }
}
